<annotation>
  <folder>images</folder>
  <filename>000014.png</filename>
  <segmented>0</segmented>
  <size>
    <width>500</width>
    <height>320</height>
    <depth>3</depth>
  </size>
  <object>
    <name>daisy</name>
    <pose>Unspecified</pose>
    <truncated>0</truncated>
    <difficult>0</difficult>
    <bndbox>
      <xmin>29</xmin>
      <ymin>28</ymin>
      <xmax>248</xmax>
      <ymax>236</ymax>
    </bndbox>
  </object>
  <object>
    <name>daisy</name>
    <pose>Unspecified</pose>
    <truncated>0</truncated>
    <difficult>0</difficult>
    <bndbox>
      <xmin>218</xmin>
      <ymin>102</ymin>
      <xmax>397</xmax>
      <ymax>274</ymax>
    </bndbox>
  </object>
</annotation>
